{
  "name": "@polyseam/cliffy-provider-gh-releases",
  "version": "0.1.0",
  "tasks": {
    "demo": "deno run -A ./demo/demo.ts"
  },
  "exports": "./mod.ts",
  "exclude": [
    "demo",
    "test",
    "demo-distance"
  ],
  "imports": {
    "@cliffy/ansi": "jsr:@cliffy/ansi@^1.0.0-rc.4",
    "@cliffy/command": "jsr:@cliffy/command@^1.0.0-rc.4",
    "@polyseam/inflate-response": "jsr:@polyseam/inflate-response@^1.1.2",
    "@std/cli": "jsr:@std/cli@^0.221.0",
    "@std/fs": "jsr:@std/fs@^0.221.0",
    "@std/semver": "jsr:@std/semver@^0.221.0"
  }
}
